ExtendedDiagramIcons/__init__.py
ExtendedDiagramIcons/digitalocean/__init__.py
ExtendedDiagramIcons/dnsproviders/__init__.py
ExtendedDiagramIcons/dnsproviders/namecheap.py
ExtendedDiagramIcons/generic/__init__.py
ExtendedDiagramIcons/octopusdeploy/__init__.py
resources/digitalocean/project.png
resources/dnsproviders/namecheap/namecheap_api.png
resources/dnsproviders/namecheap/namecheap_domain.png
resources/dnsproviders/namecheap/provider.png
resources/generic/github.png
resources/generic/jira.png
resources/generic/report_portal.png
resources/generic/software_engineer.png
resources/octopusdeploy/octopus_deploy.png
resources/octopusdeploy/octopus_server_node.png
resources/octopusdeploy/octopus_worker_node.png
resources/octopusdeploy/octopus_worker_pool.png
resources/octopusdeploy/pipeline.png
resources/octopusdeploy/release.png
scripts/__init__.py
scripts/badge.py
scripts/generate.py
scripts/resource.py
scripts/update.py
tests/__init__.py
tests/tests.py
ExtendedDiagramIcons-1.2.4.dist-info/LICENSE
ExtendedDiagramIcons-1.2.4.dist-info/METADATA
ExtendedDiagramIcons-1.2.4.dist-info/WHEEL
ExtendedDiagramIcons-1.2.4.dist-info/top_level.txt
ExtendedDiagramIcons-1.2.4.dist-info/RECORD
